README.md
setup.py
mtcnn_onnxruntime.egg-info/PKG-INFO
mtcnn_onnxruntime.egg-info/SOURCES.txt
mtcnn_onnxruntime.egg-info/dependency_links.txt
mtcnn_onnxruntime.egg-info/requires.txt
mtcnn_onnxruntime.egg-info/top_level.txt
mtcnn_ort/__init__.py
mtcnn_ort/mtcnn_ort.py
mtcnn_ort/onet.onnx
mtcnn_ort/onnx_runner.py
mtcnn_ort/pnet.onnx
mtcnn_ort/rnet.onnx