Metadata-Version: 2.1
Name: mtcnn-onnxruntime
Version: 0.0.1
Summary: MTCNN face detection using onnx runtime or OpenCV
Home-page: https://github.com/yiyuezhuo/mtcnn-onnxruntime
Author: linxiaohui, yiyuezhuo
Author-email: yiyuezhuo@gmail.com
License: UNKNOWN
Platform: UNKNOWN
Classifier: Programming Language :: Python :: 3
Classifier: Programming Language :: Python :: 3.6
Classifier: Programming Language :: Python :: 3.8
Classifier: License :: OSI Approved :: MIT License
Classifier: Operating System :: POSIX :: Linux
Classifier: Operating System :: Microsoft :: Windows
Classifier: Operating System :: MacOS :: MacOS X
Requires-Python: >=3.6
Provides-Extra: cpu
Provides-Extra: gpu
